[{"id":1,"name":"Loren Thaim","age":42,"gender":"Male","bio":"Reverse-engineered exuding toolset","img": "https://randomuser.me/api/portraits/men/15.jpg"},
{"id":2,"name":"Nikos Williscroft","age":56,"gender":"Male","bio":"Sharable tran2ional local area network","img": "https://randomuser.me/api/portraits/men/16.jpg"},
{"id":3,"name":"Randall Trebbett","age":60,"gender":"Male","bio":"Proactive cohesive parallelism","img": "https://randomuser.me/api/portraits/men/17.jpg"},
{"id":4,"name":"Kalindi Eynald","age":45,"gender":"Female","bio":"Monitored foreground circuit","img": "https://randomuser.me/api/portraits/women/12.jpg"},
{"id":5,"name":"Alecia Andrioni","age":51,"gender":"Female","bio":"Cross-platform reciprocal initiative","img": "https://randomuser.me/api/portraits/women/13.jpg"},
{"id":6,"name":"Lanna Betts","age":41,"gender":"Female","bio":"Fundamental human-resource neural-net","img": "https://randomuser.me/api/portraits/women/14.jpg"},
{"id":7,"name":"Eleanor Faucherand","age":41,"gender":"Female","bio":"Configurable human-resource software","img": "https://randomuser.me/api/portraits/women/15.jpg"},
{"id":8,"name":"Appolonia Radbourne","age":57,"gender":"Female","bio":"Ameliorated incremental projection","img": "https://randomuser.me/api/portraits/women/16.jpg"},
{"id":9,"name":"Aldon Tortoishell","age":47,"gender":"Male","bio":"Innovative 4th generation Graphical User Interface","img": "https://randomuser.me/api/portraits/men/18.jpg"},
{"id":10,"name":"Padgett Neesam","age":44,"gender":"Male","bio":"Automated multi-tasking frame","img": "https://randomuser.me/api/portraits/men/19.jpg"},
]
